{
  "type": "geolosys:deposit_layer",
  "config": {
    "yMin": 30,
    "yMax": 50,
    "radius": 4,
    "depth": 5,
    "dimensions": {
      "isBlacklist": false,
      "filter": [
        "overworld"
      ]
    },
    "blocks": [
      {
        "block": "geolosys:bituminous_coal_ore",
        "chance": 0.55
      },
      {
        "block": null,
        "chance": 0.45
      }
    ],
    "samples": [
      {
        "block": "geolosys:bituminous_coal_ore_sample",
        "chance": 1.0
      }
    ],
    "generationWeight": 5
  }
}